{"info":{"_postman_id":"d77cc5d8-d77b-44a0-afde-9f88810a8935","name":"Intellisphere API","description":"Esempio di chiamate all'Engine di memori.ai.\n\nLa documentazione può essere trovata al link\nhttps://engine.memori.ai/swagger/index.html","schema":"https://schema.getpostman.com/json/collection/v2.1.0/collection.json"},"item":[{"name":"Open the Memori Intellisphere","event":[{"listen":"test","script":{"exec":["var jsonData = JSON.parse(responseBody);\r","var sessionID = jsonData.sessionID;\r","postman.setEnvironmentVariable(\"sessionID\", sessionID);\r","console.log(\"sessionId:\" + sessionID);"],"type":"text/javascript"}}],"request":{"method":"POST","header":[],"body":{"mode":"raw","raw":"{\r\n    \"memoriId\": \"72587d1b-a002-4b87-aee8-71b8d9469bec\",\r\n    \"password\": \"undefined\",\r\n    \"birthDate\": \"1986-04-24T13:38:07.728Z\"\r\n}","options":{"raw":{"language":"json"}}},"url":{"raw":"https://backend.memori.ai/memori/v2/session","protocol":"https","host":["backend","memori","ai"],"path":["memori","v2","session"]}},"response":[]},{"name":"Make a question","event":[{"listen":"test","script":{"exec":[""],"type":"text/javascript"}}],"request":{"method":"POST","header":[],"body":{"mode":"raw","raw":"{\r\n    \"text\": \"Write here your text\"\r\n}","options":{"raw":{"language":"json"}}},"url":{"raw":"https://backend.memori.ai/memori/v2/TextEnteredEvent/{{sessionID}}","protocol":"https","host":["backend","memori","ai"],"path":["memori","v2","TextEnteredEvent","{{sessionID}}"]}},"response":[]}]}